{"type":"FeatureCollection", "features": [
{"type":"Feature","geometry":{"type":"Point","coordinates":[15000071.069404507,-2839834.102753663]},"properties":{"PID":"P2","ID":"TSR_2_1","TITLE":"Emergency care identifying and prioritising action to save fauna species at acute risk of extinction","MORK1":"prioritisation","MORK2":"extinction","MORK3":"imperilled species","MORK4":"Top twenty threatened species","MORK5":"butterflies","MORK6":"vertebrates"}},
{"type":"Feature","geometry":{"type":"Point","coordinates":[16314684.122327533,-5171423.883113976]},"properties":{"PID":"P2","ID":"TSR_2_2","TITLE":"Tackling threats to endangered hollow-nesting birds","MORK1":"sugar glider","MORK2":"nest box","MORK3":"orange-bellied parrot","MORK4":"swift parrot","MORK5":"invasive species","MORK6":"forty-spotted pardalote"}},
{"type":"Feature","geometry":{"type":"Point","coordinates":[11760077.977370476,-1174331.6932959817]},"properties":{"PID":"P2","ID":"TSR_2_3_1","TITLE":"Island-wide spatial conservation planning for Christmas Island","MORK1":"island conservation","MORK2":"spatial planning analysis","MORK3":"distribution model","MORK4":"policy","MORK5":"modelling","MORK6":" "}},
{"type":"Feature","geometry":{"type":"Point","coordinates":[11760077.977370476,-1174331.6932959817]},"properties":{"PID":"P2","ID":"TSR_2_3_2","TITLE":"Options beyond captivity for two critically endangered Christmas Island reptiles","MORK1":"island conservation","MORK2":"captive breeding","MORK3":"extinction","MORK4":"Cocos (Keeling) Islands","MORK5":"blue-tailed skink","MORK6":"Lister's gecko"}},
{"type":"Feature","geometry":{"type":"Point","coordinates":[11760077.977370476,-1174331.6932959817]},"properties":{"PID":"P2","ID":"TSR_2_3_3","TITLE":"Optimising the benefts of feral cat contol on Christmas Island","MORK1":"island conservation","MORK2":"feral cat","MORK3":"rat","MORK4":"meso-predator","MORK5":"eradication","MORK6":"bird"}},
{"type":"Feature","geometry":{"type":"Point","coordinates":[11760077.977370476,-1174331.6932959817]},"properties":{"PID":"P2","ID":"TSR_2_3_4","TITLE":"Conservation of Christmas Island flying-foxes","MORK1":"island conservation","MORK2":"flying fox","MORK3":"structured decision making","MORK4":"managing threats","MORK5":"decision support tool","MORK6":"expert elicitation"}},
{"type":"Feature","geometry":{"type":"Point","coordinates":[11760077.977370476,-1174331.6932959817]},"properties":{"PID":"P2","ID":"TSR_2_3_5","TITLE":"Combatting an emerging disease threatening endangered Christmas Island reptiles","MORK1":"island conservation","MORK2":"enterococcus","MORK3":"Lister's gecko","MORK4":"blue-tailed skink","MORK5":"disease","MORK6":"captive breeding"}},
{"type":"Feature","geometry":{"type":"Point","coordinates":[14820498.464821104,-1619003.091113984]},"properties":{"PID":"P1","ID":"TSR_1_1_1","TITLE":"Responses of threatened species to cats and fire management in Kakadu and northern savannas","MORK1":"feral cat","MORK2":"fire management","MORK3":"predator exclosure","MORK4":"dingo","MORK5":"savanna","MORK6":"mammals"}},
{"type":"Feature","geometry":{"type":"Point","coordinates":[15532085.344934005,-3140151.9106890582]},"properties":{"PID":"P1","ID":"TSR_1_1_4","TITLE":"The role of feral predators in disrupting small vertebrate communities in arid South Australia","MORK1":"community ecology","MORK2":"mammals","MORK3":"predation","MORK4":"refuge","MORK5":"predator control","MORK6":"kowari"}},
{"type":"Feature","geometry":{"type":"Point","coordinates":[16107838.915560817,-1652510.3426463315]},"properties":{"PID":"P1","ID":"TSR_1_4_3","TITLE":"Understanding and combating Myrtle Rust","MORK1":"disease","MORK2":"myrtle rust","MORK3":"Myrtaceae","MORK4":"rainforest","MORK5":"database","MORK6":"extinction"}},
{"type":"Feature","geometry":{"type":"Point","coordinates":[16015885.025784947,-4521830.175769066]},"properties":{"PID":"P3","ID":"TSR_3_2_4","TITLE":"Ecosystem Accounts for the Victorian Central Highlands","MORK1":"monitoring","MORK2":"environmental accounting","MORK3":"carbon","MORK4":"hollow-bearing trees","MORK5":"water management","MORK6":"leadbeater's possum"}},
{"type":"Feature","geometry":{"type":"Point","coordinates":[14567526.469254633,-2891320.833367164]},"properties":{"PID":"P3","ID":"TSR_3_2_5","TITLE":"Arid Zone Monitoring: surveys for vertebrates across arid and semi-arid zones","MORK1":"monitoring","MORK2":"arid zone","MORK3":"Indigenous rangers","MORK4":"distribution model","MORK5":"indigenous knowledge","MORK6":"database"}},
{"type":"Feature","geometry":{"type":"Point","coordinates":[16621750.990088886,-4001279.2714511356]},"properties":{"PID":"P3","ID":"TSR_3_2_6","TITLE":"Evidence-based management protocols for recovery of multiple threatened woodland birds","MORK1":"woodland birds","MORK2":"decision support tool","MORK3":"monitoring","MORK4":"conservation actions","MORK5":"adaptive management","MORK6":"noisy miner"}},
{"type":"Feature","geometry":{"type":"Point","coordinates":[16244575.7267376,-4517029.309808821]},"properties":{"PID":"P3","ID":"TSR_3_3_2","TITLE":"Adaptive management for threatened mammals in the Victorian Central Highlands","MORK1":"leadbeater's possum","MORK2":"greater glider","MORK3":"wet ash forests","MORK4":"recovery planning","MORK5":"hollow-bearing trees","MORK6":"adaptive management"}},
{"type":"Feature","geometry":{"type":"Point","coordinates":[13197859.93110479,-3717786.635134169]},"properties":{"PID":"P3","ID":"TSR_3_3_5","TITLE":"Recovering malleefowl with adatpvie management of feral predators","MORK1":"malleefowl","MORK2":"feral predator control","MORK3":"fox","MORK4":"feral cat","MORK5":"citizen science","MORK6":"baiting"}},
{"type":"Feature","geometry":{"type":"Point","coordinates":[16516467.43137679,-4308069.332789638]},"properties":{"PID":"P3","ID":"TSR_3_3_6","TITLE":"Adaptive reintroduction strategies for the northern corroboree frog","MORK1":"adaptive management","MORK2":"disease","MORK3":"reintroduction","MORK4":"translocation","MORK5":"frog","MORK6":"chytrid"}},
{"type":"Feature","geometry":{"type":"Point","coordinates":[13047323.453671554,-3863494.9100620933]},"properties":{"PID":"P4","ID":"TSR_4_1_7","TITLE":"Enhancing ecosystem function by reintroductions of digging mammals","MORK1":"restoration","MORK2":"translocation","MORK3":"quenda","MORK4":"ecosystem engineer","MORK5":"bettongs","MORK6":"bioturbation"}},
{"type":"Feature","geometry":{"type":"Point","coordinates":[15724494.668633759,-3943443.4897924233]},"properties":{"PID":"P4","ID":"TSR_4_4_2","TITLE":"Modelling of biophysical contraints on predators","MORK1":"refuge","MORK2":"feral cat","MORK3":"environmental tolerance","MORK4":"drought","MORK5":"biophysical model","MORK6":" "}},
{"type":"Feature","geometry":{"type":"Point","coordinates":[16984373.354032625,-3089346.4094588994]},"properties":{"PID":"P4","ID":"TSR_4_4_4","TITLE":"Climate refuges and causes of distribution limits for antechinus","MORK1":"refuge","MORK2":"climate change","MORK3":"drought","MORK4":"montane rainforest","MORK5":"antechinus","MORK6":"cloud forest"}},
{"type":"Feature","geometry":{"type":"Point","coordinates":[15706367.74554659,-3926468.175704877]},"properties":{"PID":"P1","ID":"TSR_1_1_5","TITLE":"Feral predators in south-east Australia: Towards and beyond the fence strategy","MORK1":"critical weight range mammals","MORK2":"fox","MORK3":"feral cat","MORK4":"density estimation","MORK5":"spatial ecology","MORK6":"baiting"}},
{"type":"Feature","geometry":{"type":"Point","coordinates":[15239097.568470702,-3544426.6126237838]},"properties":{"PID":"P1","ID":"TSR_1_1_6","TITLE":"Integrated management of feral herbivores and feral predators","MORK1":"camera trap","MORK2":"rabbit control","MORK3":"feral predator control","MORK4":"GPS tracking","MORK5":"feral cat","MORK6":"drought"}},
{"type":"Feature","geometry":{"type":"Point","coordinates":[15782435.820771048,-4235857.955481431]},"properties":{"PID":"P1","ID":"TSR_1_2_2","TITLE":"Adaptive management of endangered Buloke Woodlands","MORK1":"adaptive management","MORK2":"restoration","MORK3":"threatened ecological communities","MORK4":"herbivory","MORK5":"buloke woodlands","MORK6":" "}},
{"type":"Feature","geometry":{"type":"Point","coordinates":[16340949.378164204,-4478122.02917352]},"properties":{"PID":"P1","ID":"TSR_1_2_3","TITLE":"Supporting alpine peatland recovery by prioritising action on threats","MORK1":"threat management","MORK2":"restoration","MORK3":"threatened ecological communities","MORK4":"alpine peatlands","MORK5":"ecosystem recovery","MORK6":"water quality"}},
{"type":"Feature","geometry":{"type":"Point","coordinates":[15977337.122769231,-4680125.297141054]},"properties":{"PID":"P1","ID":"TSR_1_3_2","TITLE":"Fire and invasive predators","MORK1":"fire management","MORK2":"fox","MORK3":"feral cat","MORK4":"southern brown bandicoot","MORK5":"integrated threat management","MORK6":"decision support tool"}},
{"type":"Feature","geometry":{"type":"Point","coordinates":[16212126.87220098,-1922353.9464045446]},"properties":{"PID":"P1","ID":"TSR_1_3_3","TITLE":"Fire, predators and the endangered northern bettong","MORK1":"fire management","MORK2":"northern quoll","MORK3":"northern bettong","MORK4":"feral cat","MORK5":"predator control","MORK6":"habitat management"}},
{"type":"Feature","geometry":{"type":"Point","coordinates":[15000071.069404507,-2839834.102753663]},"properties":{"PID":"P1","ID":"TSR_1_4_2","TITLE":"The role of toxoplasmosis in mammal declines","MORK1":"feral cat","MORK2":"Toxoplasmosis","MORK3":"mammals","MORK4":"disease","MORK5":"distribution model","MORK6":" "}},
{"type":"Feature","geometry":{"type":"Point","coordinates":[11760077.977370476,-1174331.6932959817]},"properties":{"PID":"P2","ID":"TSR_2_3_6","TITLE":"Christmas Island frigatebird: workshop focusing on research and management priorities","MORK1":"recovery planning","MORK2":"GPS tracking","MORK3":"breeding","MORK4":"island conservation","MORK5":"Indonesia","MORK6":"fishing"}},
{"type":"Feature","geometry":{"type":"Point","coordinates":[15000071.069404507,-2839834.102753663]},"properties":{"PID":"P2","ID":"TSR_2_4","TITLE":"National Action Plan for Australias most imperilled plants","MORK1":"extinction","MORK2":"plants","MORK3":"national action plan","MORK4":"IUCN Red List","MORK5":"critically endangered","MORK6":" "}},
{"type":"Feature","geometry":{"type":"Point","coordinates":[15000071.069404507,-2839834.102753663]},"properties":{"PID":"P3","ID":"TSR_3_1","TITLE":"Developing a threatened species index","MORK1":"threatened species index","MORK2":"monitoring","MORK3":"information gap analysis","MORK4":"threatened species strategy","MORK5":"science communication","MORK6":" "}},
{"type":"Feature","geometry":{"type":"Point","coordinates":[16770456.658309376,-4118873.453255524]},"properties":{"PID":"P3","ID":"TSR_3_2_2_1","TITLE":"Using reintroductions to understand causes of mammal declines and extinctions at Booderee National Park","MORK1":"reintroduction","MORK2":"quoll","MORK3":"predator control","MORK4":"bandicoot","MORK5":"monitoring","MORK6":"species recovery"}},
{"type":"Feature","geometry":{"type":"Point","coordinates":[14753105.241944157,-1495323.6177019184]},"properties":{"PID":"P3","ID":"TSR_3_2_2_3","TITLE":"A tool for evaluating biodiversity monitoring programs in national parks","MORK1":"monitoring","MORK2":"statistical power","MORK3":"surveys","MORK4":"ecological evidence","MORK5":"detectability","MORK6":"mammals"}},
{"type":"Feature","geometry":{"type":"Point","coordinates":[15000071.069404507,-2839834.102753663]},"properties":{"PID":"P3","ID":"TSR_3_3_1","TITLE":"Practical adaptive management to improve threatened species conservation programs","MORK1":"monitoring","MORK2":"adaptive management","MORK3":"management","MORK4":"adaptive monitoring","MORK5":"species recovery","MORK6":" "}},
{"type":"Feature","geometry":{"type":"Point","coordinates":[16497661.334284587,-3678569.0112214573]},"properties":{"PID":"P3","ID":"TSR_3_3_7","TITLE":"Mitigating and managing barriers to fish passage and improving river connectivity","MORK1":"fish","MORK2":"cold water pollution","MORK3":"water management","MORK4":"environmental flows","MORK5":"swim performance","MORK6":"freshwater"}},
{"type":"Feature","geometry":{"type":"Point","coordinates":[16605550.744831476,-4187370.3146283324]},"properties":{"PID":"P4","ID":"TSR_4_1_2","TITLE":"Reintroductions inside and outside the fences in the ACT","MORK1":"translocation","MORK2":"reintroduction","MORK3":"fenced reserve","MORK4":"ecosystem engineer","MORK5":"predator control","MORK6":"predator exclosure"}},
{"type":"Feature","geometry":{"type":"Point","coordinates":[12894762.501217514,-3470118.5069874306]},"properties":{"PID":"P4","ID":"TSR_4_1_3","TITLE":"Safe havens for vulnerable mammals","MORK1":"refuge","MORK2":"conservation management","MORK3":"predator exclosure","MORK4":"monitoring","MORK5":"critical weight range mammals","MORK6":"translocation"}},
{"type":"Feature","geometry":{"type":"Point","coordinates":[16348213.171325304,-4481197.442067854]},"properties":{"PID":"P4","ID":"TSR_4_1_5","TITLE":"Decisions for ex situ management of threatened species","MORK1":"captive breeding","MORK2":"decision support tool","MORK3":"management plans","MORK4":"decision tree","MORK5":" ","MORK6":" "}},
{"type":"Feature","geometry":{"type":"Point","coordinates":[15000071.069404507,-2839834.102753663]},"properties":{"PID":"P5","ID":"TSR_5_2","TITLE":"Improving conservation assessments and policy options for poorly known species","MORK1":"plants","MORK2":"data deficient species","MORK3":"policy","MORK4":"taxonomic bias","MORK5":"imperilled species","MORK6":"invertebrates"}},
{"type":"Feature","geometry":{"type":"Point","coordinates":[15000071.069404507,-2839834.102753663]},"properties":{"PID":"P6","ID":"TSR_6_1","TITLE":"The economics of threatened species management","MORK1":"benefits","MORK2":"cost models","MORK3":"valuation","MORK4":"non-market value","MORK5":"risk-based decision framework","MORK6":"Benefit Transfer Tools"}},
{"type":"Feature","geometry":{"type":"Point","coordinates":[15000071.069404507,-2839834.102753663]},"properties":{"PID":"P6","ID":"TSR_6_3_1","TITLE":"Improving communication for threatened species conservation","MORK1":"science communication","MORK2":"public engagement","MORK3":"message framing","MORK4":"conservation opportunities","MORK5":"community engagement","MORK6":"conservation marketing"}},
{"type":"Feature","geometry":{"type":"Point","coordinates":[15000071.069404507,-2839834.102753663]},"properties":{"PID":"P6","ID":"TSR_6_3_2","TITLE":"Identifying new conservation opportunities","MORK1":"science communication","MORK2":"public engagement","MORK3":"education","MORK4":"conservation opportunities","MORK5":"business","MORK6":"agriculture"}},
{"type":"Feature","geometry":{"type":"Point","coordinates":[16381826.494918853,-3339433.268869086]},"properties":{"PID":"P6","ID":"TSR_6_3_3","TITLE":"Urban flying-fox roost management","MORK1":"human-wildlife conflict","MORK2":"community values","MORK3":"public engagement","MORK4":"urban ecology","MORK5":"framing","MORK6":" "}},
{"type":"Feature","geometry":{"type":"Point","coordinates":[16164995.802406391,-4572730.14553009]},"properties":{"PID":"P6","ID":"TSR_6_3_4","TITLE":"Iconic species in schools","MORK1":"connection to nature","MORK2":"cultural heritage","MORK3":"indigenous knowledge","MORK4":"education","MORK5":"community engagement","MORK6":"stewardship"}},
{"type":"Feature","geometry":{"type":"Point","coordinates":[15000071.069404507,-2839834.102753663]},"properties":{"PID":"P6","ID":"TSR_6_3_5","TITLE":"Targeting Australia's highest biodiversity impact behaviours","MORK1":"human behaviour","MORK2":"marketing","MORK3":"conservation messaging","MORK4":"community engagement","MORK5":"conservation psychology","MORK6":" "}},
{"type":"Feature","geometry":{"type":"Point","coordinates":[15286325.422296625,-4271440.996637586]},"properties":{"PID":"P1","ID":"TSR_1_1_10","TITLE":"Response of the Kangaroo Island Dunnart and other threatened species to a cat eradication program","MORK1":"Kangaroo Island dunnart","MORK2":"monitoring","MORK3":"eradication","MORK4":"mammals","MORK5":"predator control","MORK6":"feral cat"}},
{"type":"Feature","geometry":{"type":"Point","coordinates":[15734860.307402685,-2680848.7108398336]},"properties":{"PID":"P1","ID":"TSR_1_1_11","TITLE":"Conservation of the Night Parrot","MORK1":"night parrot","MORK2":"feral cat","MORK3":"dingo","MORK4":"meso-predator","MORK5":"carrion","MORK6":"feral predator control"}},
{"type":"Feature","geometry":{"type":"Point","coordinates":[14579215.487078322,-1301373.911526647]},"properties":{"PID":"P1","ID":"TSR_1_1_12","TITLE":"Mitigating cat impacts on the brush-tailed rabbit-rat","MORK1":"brush-tailed rabbit-rat","MORK2":"feral cat","MORK3":"feral predator control","MORK4":"fire management","MORK5":"Tiwi Islands","MORK6":"mammals"}},
{"type":"Feature","geometry":{"type":"Point","coordinates":[12906765.406841293,-2465131.020576158]},"properties":{"PID":"P1","ID":"TSR_1_1_7","TITLE":"Some responses of the threatened Northern Quoll to a large-scale cat baiting program in the Pilbara","MORK1":"baiting","MORK2":"feral cat","MORK3":"northern quoll","MORK4":"predator control","MORK5":" ","MORK6":" "}},
{"type":"Feature","geometry":{"type":"Point","coordinates":[13061594.129525948,-3469211.8686527405]},"properties":{"PID":"P4","ID":"TSR_4_1_11","TITLE":"Re-establishing critical weight range mammals in northern wheatbelt of Western Australia: reintroductions to  safe haven free of introduced predators","MORK1":"refuge","MORK2":"reintroduction","MORK3":"predator exclosure","MORK4":"critical weight range mammals","MORK5":"conservation management","MORK6":"translocation"}},
{"type":"Feature","geometry":{"type":"Point","coordinates":[16395481.269390257,-5371179.667600283]},"properties":{"PID":"P4","ID":"TSR_4_2_2","TITLE":"Actions for saving threatened species on priority islands","MORK1":"island conservation","MORK2":"invasive species","MORK3":"feral cat","MORK4":"rat","MORK5":"eradication","MORK6":"decision support tool"}},
{"type":"Feature","geometry":{"type":"Point","coordinates":[17684462.851698752,-7289999.5001501655]},"properties":{"PID":"P4","ID":"TSR_4_2_3","TITLE":"Post eradication monitoring and translocation on islands","MORK1":"island conservation","MORK2":"eradication","MORK3":"invertebrates","MORK4":"monitoring","MORK5":"burrowing petrels","MORK6":"rabbits"}},
{"type":"Feature","geometry":{"type":"Point","coordinates":[18695932.368227523,-3379948.5199465733]},"properties":{"PID":"P4","ID":"TSR_4_2_4","TITLE":"Norfolk Island threatened species conservation","MORK1":"conservation","MORK2":"plants","MORK3":"knowledge gaps","MORK4":"island management","MORK5":"exclusion experiments","MORK6":"invasive species"}},
{"type":"Feature","geometry":{"type":"Point","coordinates":[13832316.201185733,-1804215.5459560724]},"properties":{"PID":"P4","ID":"TSR_4_2_5","TITLE":"Protecting threatened quolls and other biodiversity on Kimberley islands from cane toads","MORK1":"northern quoll","MORK2":"translocation","MORK3":"invasive species","MORK4":"refuge","MORK5":"spatial planning analysis","MORK6":"cane toad"}},
{"type":"Feature","geometry":{"type":"Point","coordinates":[15000071.069404507,-2839834.102753663]},"properties":{"PID":"P4","ID":"TSR_4_4_5","TITLE":"Understanding and prioritising refuges across Australia","MORK1":"refuge","MORK2":"feral cat","MORK3":"fire","MORK4":"database","MORK5":"drought","MORK6":"feral predator"}},
{"type":"Feature","geometry":{"type":"Point","coordinates":[16244762.654121622,-3902780.613015537]},"properties":{"PID":"P4","ID":"TSR_4_4_7","TITLE":"Threatened bird conservation in Murray-Darling Basin wetland and floodplain habitat?á","MORK1":"wetland","MORK2":"woodland birds","MORK3":"distribution model","MORK4":"drought","MORK5":"floodplain","MORK6":"spatial prioritisation"}},
{"type":"Feature","geometry":{"type":"Point","coordinates":[15000071.069404507,-2839834.102753663]},"properties":{"PID":"P4","ID":"TSR_4_4_10","TITLE":"Modelling species distributions under environmental change","MORK1":"distribution model","MORK2":"climate change","MORK3":"decision support tool","MORK4":"critical habitat","MORK5":" ","MORK6":" "}},
{"type":"Feature","geometry":{"type":"Point","coordinates":[15000071.069404507,-2839834.102753663]},"properties":{"PID":"P5","ID":"TSR_5_1","TITLE":"Better offsets for threatened species","MORK1":"offsets","MORK2":"malleefowl","MORK3":"night parrot","MORK4":"brigalow reptiles","MORK5":"northern quoll","MORK6":"black-cockatoo"}},
{"type":"Feature","geometry":{"type":"Point","coordinates":[16468906.392201563,-4121196.3194658784]},"properties":{"PID":"P1","ID":"TSR_1_2_1","TITLE":"Conservation of box gum grassy woodlands and the threatened species within them","MORK1":"critical habitat","MORK2":"threatened ecological communities","MORK3":"ecosystems","MORK4":"reptiles","MORK5":"woodland birds","MORK6":" "}},
{"type":"Feature","geometry":{"type":"Point","coordinates":[16468906.392201563,-4121196.3194658784]},"properties":{"PID":"P1","ID":"TSR_1_2_1_2","TITLE":"Can culling noisy miners benefit threatened woodland birds?","MORK1":"noisy miner","MORK2":"woodland birds","MORK3":"overabundant native species","MORK4":"box gum grassy woodland","MORK5":"restoration","MORK6":"threatened ecological communities"}},
{"type":"Feature","geometry":{"type":"Point","coordinates":[16468906.392201563,-4121196.3194658784]},"properties":{"PID":"P1","ID":"TSR_1_2_1_3","TITLE":"Survival and persistence of woodland birds in restoration plantings","MORK1":"woodland birds","MORK2":"temperate woodlands","MORK3":"restoration","MORK4":"monitoring","MORK5":"bird breeding","MORK6":"box gum grassy woodlands"}},
{"type":"Feature","geometry":{"type":"Point","coordinates":[16468906.392201563,-4121196.3194658784]},"properties":{"PID":"P1","ID":"TSR_1_2_1_4","TITLE":"How bird communities change in relation to vegetation change","MORK1":"woodland birds","MORK2":"temperate woodlands","MORK3":"threatened ecological communities","MORK4":"ecological recovery","MORK5":"restoration","MORK6":"management"}},
{"type":"Feature","geometry":{"type":"Point","coordinates":[16375104.673669295,-4308692.504975088]},"properties":{"PID":"P1","ID":"TSR_1_2_1_5","TITLE":"Testing the effectiveness of nest boxes for threatened species","MORK1":"nest box","MORK2":"hollow-bearing trees","MORK3":"farms","MORK4":"arboreal mammals","MORK5":"offsets","MORK6":"temperate woodlands"}},
{"type":"Feature","geometry":{"type":"Point","coordinates":[16481911.670389514,-4139286.5924868975]},"properties":{"PID":"P1","ID":"TSR_1_2_1_6","TITLE":"Enhancing critical habitat for the Pink-tailed Worm-lizard in agricultural landscapes","MORK1":"pink-tailed worm-lizard","MORK2":"restoration","MORK3":"box gum grassy woodlands","MORK4":"rocky outcrops","MORK5":"grazing","MORK6":"distribution model"}},
{"type":"Feature","geometry":{"type":"Point","coordinates":[16651826.203809913,-3955066.2739174394]},"properties":{"PID":"P1","ID":"TSR_1_2_1_7","TITLE":"Restoring the endangered Yass Daisy","MORK1":"adaptive management","MORK2":"restoration","MORK3":"box gum grassy woodlands","MORK4":"yass daisy","MORK5":"button wrinklewort","MORK6":"translocation"}},
{"type":"Feature","geometry":{"type":"Point","coordinates":[16302233.263758149,-4133363.1869267737]},"properties":{"PID":"P1","ID":"TSR_1_2_4","TITLE":"Ecosystem Accounts in Box Gum Grassy Woodlands","MORK1":"ecosystem accounting","MORK2":"policy","MORK3":"box gum grassy woodlands","MORK4":"ecosystem services","MORK5":"natural capital","MORK6":"ecosystem management"}},
{"type":"Feature","geometry":{"type":"Point","coordinates":[15000071.069404507,-2839834.102753663]},"properties":{"PID":"P6","ID":"TSR_6_4","TITLE":"Learning from success and failure in threatened species conservation","MORK1":"recovery planning","MORK2":"governance","MORK3":"conservation research","MORK4":"conservation success","MORK5":"leadership","MORK6":"community engagement"}},
{"type":"Feature","geometry":{"type":"Point","coordinates":[16244765.516836457,-4516291.352499761]},"properties":{"PID":"P4","ID":"TSR_4_1_1","TITLE":"Safe havens for vulnerable mammals","MORK1":"mammals","MORK2":"fenced reserve","MORK3":"islands","MORK4":"predator exclosure","MORK5":"decision support tool","MORK6":"spatial planning analysis"}},
{"type":"Feature","geometry":{"type":"Point","coordinates":[13594031.68202414,-2469684.772662284]},"properties":{"PID":"P4","ID":"TSR_4_4_6","TITLE":"Rocky refuges for mammals","MORK1":"refuge","MORK2":"vertebrates","MORK3":"fire","MORK4":"drought","MORK5":"rock outcrops","MORK6":" "}},
{"type":"Feature","geometry":{"type":"Point","coordinates":[16214262.269030875,-4450055.857905429]},"properties":{"PID":"P4","ID":"TSR_4_4_8","TITLE":"Mapping distributions, threats and opportunities to conserve the greater glider","MORK1":"greater glider","MORK2":"biophysical model","MORK3":"population viability analysis","MORK4":"distribution model","MORK5":"climate change","MORK6":"forest change model"}},
{"type":"Feature","geometry":{"type":"Point","coordinates":[14567590.82565991,-1405443.484769377]},"properties":{"PID":"P5","ID":"TSR_5_1_1","TITLE":"Strategic Planning for the Far Eastern Curlew","MORK1":"migratory shorebirds","MORK2":"offsets","MORK3":"coastal planning","MORK4":"port development","MORK5":"intertidal","MORK6":"traditional owners"}},
{"type":"Feature","geometry":{"type":"Point","coordinates":[16207090.539694455,-1968157.5997845368]},"properties":{"PID":"P3","ID":"TSR_3_2_3_1","TITLE":"Using drones for biodiversity monitoring","MORK1":"monitoring","MORK2":"drones","MORK3":"Lumholtz tree kangaroo","MORK4":"detectability","MORK5":"thermal camera","MORK6":"occupany model"}},
{"type":"Feature","geometry":{"type":"Point","coordinates":[16219786.796446128,-1956704.7512368634]},"properties":{"PID":"P3","ID":"TSR_3_2_3_2","TITLE":"Thermal imaging cameras for biodiversity monitoring","MORK1":"thermal camera","MORK2":"monitoring","MORK3":"population estimation","MORK4":"conservation technology","MORK5":"Lumholtz tree kangaroo","MORK6":"detectability"}},
{"type":"Feature","geometry":{"type":"Point","coordinates":[13130370.075579744,-3697810.842090057]},"properties":{"PID":"P4","ID":"TSR_4_1_4_1","TITLE":"Assisted colonisation of Australia's rarest reptile: The western swamp turtle","MORK1":"translocation","MORK2":"climate change","MORK3":"freshwater","MORK4":"assisted colonisation","MORK5":"drought","MORK6":"reptiles"}},
{"type":"Feature","geometry":{"type":"Point","coordinates":[16415625.826481782,-4455093.624162219]},"properties":{"PID":"P4","ID":"TSR_4_1_4_2","TITLE":"Optimising the timing for assiting the colonisation of threatened montane frogs","MORK1":"alpine","MORK2":"assisted colonisation","MORK3":"climate change","MORK4":"amphibians","MORK5":"modelling","MORK6":"decision support tool"}},
{"type":"Feature","geometry":{"type":"Point","coordinates":[12812859.408171507,-4021733.627557696]},"properties":{"PID":"P4","ID":"TSR_4_1_4_3","TITLE":"Improving conservation outcomes for critically endangered white-bellied frog","MORK1":"translocation","MORK2":"reintroduction","MORK3":"amphibians","MORK4":"drought","MORK5":"captive breeding","MORK6":"frogs"}},
{"type":"Feature","geometry":{"type":"Point","coordinates":[15853752.154886477,-4469275.5538799]},"properties":{"PID":"P1","ID":"TSR_1_1_8","TITLE":"Livestock guardian dogs to protect threatened species and restore habitat","MORK1":"critical weight range mammals","MORK2":"livestock guardian dog","MORK3":"non-lethal control","MORK4":"reintroduction","MORK5":"invasive predator","MORK6":"invasive herbivore"}},
{"type":"Feature","geometry":{"type":"Point","coordinates":[13652075.282529097,-1904986.6479632705]},"properties":{"PID":"P1","ID":"TSR_1_3_5","TITLE":"Managing fire to recover monsoon vine thickets on the Dampier Peninsula","MORK1":"remote sensing","MORK2":"vine thickets","MORK3":"fire management","MORK4":"rainforest","MORK5":"recovery planning","MORK6":"Indigenous rangers"}},
{"type":"Feature","geometry":{"type":"Point","coordinates":[16971664.458239865,-3280069.8123629997]},"properties":{"PID":"P4","ID":"TSR_4_1_12","TITLE":"Reintroduction plan to rescue the northern eastern bristlebird","MORK1":"reintroduction","MORK2":"management plans","MORK3":"captive breeding","MORK4":"monitoring","MORK5":"fire management","MORK6":"eastern bristlebird"}},
{"type":"Feature","geometry":{"type":"Point","coordinates":[14752813.49732461,-1459959.3346156687]},"properties":{"PID":"P6","ID":"TSR_6_2","TITLE":"Indigenous action in threatened species research and management","MORK1":"adaptive co-management","MORK2":"knowledge sharing","MORK3":"Indigenous rangers","MORK4":"joint management","MORK5":"IUCN Green List","MORK6":"culturally significant species"}},
{"type":"Feature","geometry":{"type":"Point","coordinates":[12887997.25967668,-4027281.598006939]},"properties":{"PID":"P6","ID":"TSR_6_5","TITLE":"Citizen science for threatened species conservation and building community support","MORK1":"western ringtail possum","MORK2":"conservation actions","MORK3":"citizen science","MORK4":"monitoring","MORK5":"community engagement","MORK6":"urban ecology"}},
{"type":"Feature","geometry":{"type":"Point","coordinates":[16609504.712278936,-2696957.198415963]},"properties":{"PID":"P1","ID":"TSR_1_1_3","TITLE":"Feral cat control for threatened species in Queensland","MORK1":"feral predator control","MORK2":"feral cat","MORK3":"greater bilby","MORK4":"predation","MORK5":"baiting","MORK6":"bridled nailtail wallaby"}},
{"type":"Feature","geometry":{"type":"Point","coordinates":[16717637.523457225,-3806505.345694499]},"properties":{"PID":"P1","ID":"TSR_1_3_1","TITLE":"Fire and native flora","MORK1":"fire management","MORK2":"plants","MORK3":"Pomaderris","MORK4":"Boronia","MORK5":"fire","MORK6":"modelling"}},
{"type":"Feature","geometry":{"type":"Point","coordinates":[16898461.155282356,-3745339.547251967]},"properties":{"PID":"P1","ID":"TSR_1_4_1","TITLE":"Mitigating threats to Australian frogs","MORK1":"fire","MORK2":"frog","MORK3":"distribution model","MORK4":"chytrid","MORK5":"amphibians","MORK6":"disease"}},
{"type":"Feature","geometry":{"type":"Point","coordinates":[11760357.41086151,-1173949.069244116]},"properties":{"PID":"P2","ID":"TSR_2_3","TITLE":"Enhancing threatened species outcomes on Christmas Island","MORK1":"translocation","MORK2":"island","MORK3":"reptile","MORK4":"feral predator control","MORK5":"flying fox","MORK6":"disease"}},
{"type":"Feature","geometry":{"type":"Point","coordinates":[16044392.726030739,-1775452.4743148955]},"properties":{"PID":"P2","ID":"TSR_2_6","TITLE":"Essential research to secure the buff-breasted button quail","MORK1":"button-quail","MORK2":"threatening process","MORK3":"predator","MORK4":"distribution","MORK5":"critical habitat","MORK6":" "}},
{"type":"Feature","geometry":{"type":"Point","coordinates":[16540558.922687333,-4258002.753617981]},"properties":{"PID":"P3","ID":"TSR_3_2_8","TITLE":"Monitoring bogong moth population change","MORK1":"climate change","MORK2":"bogong moth","MORK3":"mountain pygmy possum","MORK4":"migration","MORK5":"monitoring","MORK6":"managing threats"}},
{"type":"Feature","geometry":{"type":"Point","coordinates":[17684656.99159297,-7288003.226554768]},"properties":{"PID":"P4","ID":"TSR_4_2_3_4","TITLE":"Detecting cryptic burrowing petrel recovery post-eradication in a remote landscape","MORK1":"eDNA","MORK2":"burrowing petrel","MORK3":"genetics","MORK4":"seabirds","MORK5":"feral predator","MORK6":"monitoring"}},
{"type":"Feature","geometry":{"type":"Point","coordinates":[13643796.129746806,-3151853.0233370448]},"properties":{"PID":"P7","ID":"TSR_7_2","TITLE":"Conservation actions for Threatened Ecological Communities","MORK1":" ","MORK2":"state and transition models","MORK3":"recovery planning","MORK4":"threatened ecological communities","MORK5":"expert elicitation","MORK6":"conservation actions"}},
{"type":"Feature","geometry":{"type":"Point","coordinates":[14731956.331807617,-2208663.1551178433]},"properties":{"PID":"P7","ID":"TSR_7_9","TITLE":"Integrated Enviromental Assessment","MORK1":"integrated environmental assessment","MORK2":"planning","MORK3":"decision making","MORK4":"MNES","MORK5":"development","MORK6":"de-risking investment"}},
{"type":"Feature","geometry":{"type":"Point","coordinates":[14778950.293736938,-2722110.1496997694]},"properties":{"PID":"P2","ID":"TSR_2_4_1","TITLE":"Development of a national action plan for Australian eucalypts","MORK1":"plants","MORK2":"national action plan","MORK3":"critically endangered","MORK4":"IUCN Red List","MORK5":"threats","MORK6":"extinction"}},
{"type":"Feature","geometry":{"type":"Point","coordinates":[14778950.293736938,-2722110.1496997694]},"properties":{"PID":"P6","ID":"TSR_6_6","TITLE":"Key factors for effective partner integration and governance for threatened species recovery","MORK1":"trust building","MORK2":"partnership","MORK3":"recovery planning","MORK4":"collaboration","MORK5":"governance","MORK6":"co-investment"}},
{"type":"Feature","geometry":{"type":"Point","coordinates":[15000071.069404507,-2839834.102753663]},"properties":{"PID":"P7","ID":"TSR_7_1","TITLE":"Methods for measuring uptake and outcomes from environmental research","MORK1":"framework","MORK2":"partnership","MORK3":"research impact","MORK4":"outcomes assessment","MORK5":"monitoring","MORK6":"research uptake"}},
{"type":"Feature","geometry":{"type":"Point","coordinates":[14778950.293736938,-2722110.1496997694]},"properties":{"PID":"P7","ID":"TSR_7_3","TITLE":"Assessing biodiversity and cultural values for single-site and multi-property development proposals in northern Australia","MORK1":" ","MORK2":"strategic assessment","MORK3":"cultural values","MORK4":"environmental impact assessment","MORK5":"offsets","MORK6":"policy"}},
{"type":"Feature","geometry":{"type":"Point","coordinates":[15000071.069404507,-2839834.102753663]},"properties":{"PID":"P7","ID":"TSR_7_5","TITLE":"National monitoring priorities, process and prospectus for threatened species","MORK1":"surveys","MORK2":"monitoring","MORK3":"recovery process","MORK4":"prioritisation","MORK5":"cost models","MORK6":"sampling methods"}},
{"type":"Feature","geometry":{"type":"Point","coordinates":[15767746.399717892,-4131542.558844254]},"properties":{"PID":"P7","ID":"TSR_7_6","TITLE":"Managing impacts of feral and over-abundant herbivores on threatened species and ecological communities","MORK1":"cultural values","MORK2":"feral herbivore","MORK3":"native herbivore","MORK4":"threat abatement","MORK5":"invasive species","MORK6":"threatened ecological communities"}},
{"type":"Feature","geometry":{"type":"Point","coordinates":[15000071.069404507,-2839834.102753663]},"properties":{"PID":"P7","ID":"TSR_7_7","TITLE":"Overlaying threat, threatened species ranges, threat mitigation and conservation options - a knowledge synthesis to inform a national approach to fighting extinction","MORK1":"co-benefit","MORK2":"threat mitigation","MORK3":"synthesis","MORK4":"cost models","MORK5":"managing threats","MORK6":"recovery"}},
{"type":"Feature","geometry":{"type":"Point","coordinates":[14778950.293736938,-2722110.1496997694]},"properties":{"PID":"P7","ID":"TSR_7_8","TITLE":"Translating research findings on offsets and strategic planning to underpin continuous improvement in policy and practice","MORK1":"synthesis","MORK2":"decision making","MORK3":"capacity building","MORK4":"educational videos","MORK5":"offsets","MORK6":"policy"}},
{"type":"Feature","geometry":{"type":"Point","coordinates":[15000071.069404507,-2839834.102753663]},"properties":{"PID":"P7","ID":"TSR_7_10","TITLE":"Conservation decision making for island management: lessons learned","MORK1":"feral predator","MORK2":"decision making","MORK3":"invasive species","MORK4":"eradication","MORK5":"management","MORK6":"island conservation"}},
{"type":"Feature","geometry":{"type":"Point","coordinates":[14778950.293736938,-2722110.1496997694]},"properties":{"PID":"P1","ID":"TSR_1_4_4","TITLE":"Guidelines on how to treat Australian wildlife with sarcoptic mange","MORK1":"disease","MORK2":"sarcoptic mange","MORK3":"wombat","MORK4":"guidelines","MORK5":"treatment","MORK6":"mammals"}},
{"type":"Feature","geometry":{"type":"Point","coordinates":[14778950.293736938,-2722110.1496997694]},"properties":{"PID":"P7","ID":"TSR_7_4","TITLE":"Cat impacts and management: knowledge exchange for stakeholders","MORK1":"cat","MORK2":"local government","MORK3":"management","MORK4":"communication","MORK5":"managing threats","MORK6":"feral predator"}},
{"type":"Feature","geometry":{"type":"Point","coordinates":[16084945.065659907,-4114099.5282526165]},"properties":{"PID":"P1","ID":"TSR_1_2_5","TITLE":"Coordinated recovery planning for threatened woodlands","MORK1":"recovery planning","MORK2":"eucalypt woodlands","MORK3":"threatened ecological communities","MORK4":"state and transition models","MORK5":"expert elicitation","MORK6":"management"}},
{"type":"Feature","geometry":{"type":"Point","coordinates":[15527853.85999577,-3179616.6251974497]},"properties":{"PID":"P1","ID":"TSR_1_1_2","TITLE":"Feral cat distribution, abundance, management and impacts on threatened species: collation and analysis of data","MORK1":"feral cat","MORK2":"fox","MORK3":"dingo","MORK4":"predation","MORK5":"predator control","MORK6":"modelling"}},
{"type":"Feature","geometry":{"type":"Point","coordinates":[11760077.977370476,-1174331.6932959817]},"properties":{"PID":"P2","ID":"TSR_2_3_5","TITLE":"Combatting an emerging disease threatening endangered Christmas Island reptiles","MORK1":"island conservation","MORK2":"enterococcus","MORK3":"Lister's gecko","MORK4":"blue-tailed skink","MORK5":"disease","MORK6":"captive breeding"}},
{"type":"Feature","geometry":{"type":"Point","coordinates":[13906361.366178561,-2285421.142432493]},"properties":{"PID":"P3","ID":"TSR_3_2_7","TITLE":"Manging jilas on Ngurrara country","MORK1":"waterhole","MORK2":"desert","MORK3":"feral predator","MORK4":"fire management","MORK5":"feral herbivore","MORK6":"monitoring"}},
{"type":"Feature","geometry":{"type":"Point","coordinates":[16955317.196048625,-3646779.7409781227]},"properties":{"PID":"P8","ID":"TSR_8_5_1","TITLE":"Improving rapid busfire response for conservation of threatened species and communities","MORK1":"fire","MORK2":"recovery","MORK3":"planning","MORK4":"risk management","MORK5":"fire management","MORK6":" "}},
{"type":"Feature","geometry":{"type":"Point","coordinates":[16955317.196048625,-3646779.7409781227]},"properties":{"PID":"P8","ID":"TSR_8_4_2","TITLE":"Fire-related risks to, and conservation strategies for, ecological communities","MORK1":"rainforest","MORK2":"peatland","MORK3":"post-fire","MORK4":"World Heritage","MORK5":"threatened ecological communities","MORK6":" "}},
{"type":"Feature","geometry":{"type":"Point","coordinates":[15284642.407795524,-4272342.118171416]},"properties":{"PID":"P8","ID":"TSR_8_4_1","TITLE":"Post-fire changes in feral cat density across Kangaroo Island","MORK1":"feral cat","MORK2":"feral predator","MORK3":"post-fire","MORK4":"recovery","MORK5":"possum","MORK6":"mammals"}},
{"type":"Feature","geometry":{"type":"Point","coordinates":[17039752.546151116,-3298489.118866548]},"properties":{"PID":"P8","ID":"TSR_8_3_8","TITLE":"Survival and recovery of threatened animal species in fire-affected Gondwana Rainforests","MORK1":"rainforest","MORK2":"mammals","MORK3":"reptiles","MORK4":"frog","MORK5":"fire","MORK6":"World Heritage"}},
{"type":"Feature","geometry":{"type":"Point","coordinates":[17006510.931905296,-3354338.178420574]},"properties":{"PID":"P8","ID":"TSR_8_3_5","TITLE":"Fire and rust: The impact of myrtle rust on fire regeneration","MORK1":"myrtle rust","MORK2":"World Heritage","MORK3":"rainforest","MORK4":"disease","MORK5":"post-fire","MORK6":"impact assessment"}},
{"type":"Feature","geometry":{"type":"Point","coordinates":[16955314.632807475,-3646780.128511402]},"properties":{"PID":"P8","ID":"TSR_8_3_4","TITLE":"Estimating wildlife mortality during bushfire","MORK1":"post-fire","MORK2":"survival","MORK3":"vertebrates","MORK4":"modelling","MORK5":"recovery","MORK6":" "}},
{"type":"Feature","geometry":{"type":"Point","coordinates":[16518546.3526963,-3291027.792052741]},"properties":{"PID":"P8","ID":"TSR_8_4_5","TITLE":"Better managing fires and their impacts for koala conservation","MORK1":"koala","MORK2":"post-fire","MORK3":"recovery plan","MORK4":"fire management","MORK5":"threat management","MORK6":" "}},
{"type":"Feature","geometry":{"type":"Point","coordinates":[15000071.069404507,-2839834.102753663]},"properties":{"PID":"P8","ID":"TSR_8_4_4","TITLE":"Review of faunal responses to fire-associated management actions","MORK1":"post-fire","MORK2":"recovery","MORK3":"fire management","MORK4":"fire","MORK5":"woodland birds","MORK6":"fauna"}},
{"type":"Feature","geometry":{"type":"Point","coordinates":[16955314.632807475,-3646780.128511402]},"properties":{"PID":"P8","ID":"TSR_8_4_3","TITLE":"Managing the impacts of feral herbivores following regional-scale wildlife","MORK1":"post-fire","MORK2":"threatened ecological communities","MORK3":"MNES","MORK4":"feral herbivore","MORK5":"threate abatement","MORK6":" "}},
{"type":"Feature","geometry":{"type":"Point","coordinates":[16140594.15283329,-3421747.1577030923]},"properties":{"PID":"P8","ID":"TSR_8_3_7","TITLE":"Impacts of post-fire ash and run-off sediment on Australian freshwater aquatic fauna","MORK1":"crayfish","MORK2":"post-fire","MORK3":"physiology","MORK4":"fish","MORK5":"amphibians","MORK6":"ash sediment"}},
{"type":"Feature","geometry":{"type":"Point","coordinates":[16955314.632807475,-3646780.128511402]},"properties":{"PID":"P8","ID":"TSR_8_3_6","TITLE":"Collation of summary of 2019-20 bushfire impacts and emergency responses of freshwater fish","MORK1":"post-fire","MORK2":"fish","MORK3":"aquatic fauna","MORK4":"impact assessment","MORK5":"fire suppression","MORK6":"sediment"}},
{"type":"Feature","geometry":{"type":"Point","coordinates":[16955314.632807475,-3646780.128511402]},"properties":{"PID":"P8","ID":"TSR_8_3_3","TITLE":"Genetic assessment of priority taxa and management priorities","MORK1":"genetics","MORK2":"taxonomy","MORK3":"fire impact","MORK4":"risk assessment","MORK5":"vertebrates","MORK6":"conservation strategy"}},
{"type":"Feature","geometry":{"type":"Point","coordinates":[16955314.632807475,-3646780.128511402]},"properties":{"PID":"P8","ID":"TSR_8_3_2","TITLE":"Effect of fire severity on the response of populations of priority wildlife species","MORK1":"impact assessment","MORK2":"vertebrates","MORK3":"managing threats","MORK4":"post-fire recovery","MORK5":"spiny crayfish","MORK6":"distribution map"}},
{"type":"Feature","geometry":{"type":"Point","coordinates":[16955314.632807475,-3646780.128511402]},"properties":{"PID":"P8","ID":"TSR_8_3_1","TITLE":"Fire-affected invertebrates: priority species and management response","MORK1":"invertebrates","MORK2":"post-fire","MORK3":"recovery","MORK4":"management","MORK5":"threat assessment","MORK6":"monitoring"}},
{"type":"Feature","geometry":{"type":"Point","coordinates":[15244240.734558184,-4280294.253602082]},"properties":{"PID":"P8","ID":"TSR_8_2_1","TITLE":"Indigenous aspirations and capacity for bushfire response","MORK1":"cultural burning","MORK2":"culturally significant species","MORK3":"Indigenous knowledge","MORK4":"post-fire","MORK5":"fire management","MORK6":"Indigenous leadership"}},
{"type":"Feature","geometry":{"type":"Point","coordinates":[16955314.632807475,-3646780.128511402]},"properties":{"PID":"P8","ID":"TSR_8_1_3","TITLE":"Post-fire impact assessment for priority frogs","MORK1":"frog","MORK2":"post-fire","MORK3":"monitoring","MORK4":"impact assessment","MORK5":"recovery","MORK6":"on-ground management"}},
{"type":"Feature","geometry":{"type":"Point","coordinates":[16955314.632807475,-3646780.128511402]},"properties":{"PID":"P8","ID":"TSR_8_1_1","TITLE":"Designing rapid on-ground reconnaissance surveys for post natural disaster (fire) to assess the status of species, ecological communities, habitats and threats","MORK1":"post-fire","MORK2":"surveys","MORK3":"prioritisation","MORK4":"vertebrates","MORK5":"monitoring","MORK6":" "}},
{"type":"Feature","geometry":{"type":"Point","coordinates":[16955314.632807475,-3646780.128511402]},"properties":{"PID":"P8","ID":"TSR_8_1_2","TITLE":"Design for postfire impact monitoring, including synthesis of current monitoring projects","MORK1":"post-fire","MORK2":"monitoring","MORK3":"vertebrates","MORK4":"recovery","MORK5":"management","MORK6":"surveys"}},
{"type":"Feature","geometry":{"type":"Point","coordinates":[15734860.306539765,-2680848.711974836]},"properties":{"PID":"P2","ID":"TSR_2_5","TITLE":"Securing the Night Parrot","MORK1":"night parrot","MORK2":"fire regime","MORK3":"feral predator","MORK4":"citizen science","MORK5":"acoustic monitoring","MORK6":" "}},
{"type":"Feature","geometry":{"type":"Point","coordinates":[12842694.502323247,-3984121.03656663]},"properties":{"PID":"P4","ID":"TSR_4_1_8","TITLE":"Understanding genomic variation in the western ringtail possum for adaptive conservation","MORK1":"genetic management","MORK2":"population viability analysis","MORK3":"genetics","MORK4":"management plans","MORK5":"western ringtail possum","MORK6":" "}},
{"type":"Feature","geometry":{"type":"Point","coordinates":[13666564.563851897,-2175541.5760270865]},"properties":{"PID":"P1","ID":"TSR_1_3_4","TITLE":"Pirra Jungku (Warlu) - Contrasting the outcomes of contemporary and traditional fire management approaches in the desert","MORK1":"fire management","MORK2":"monitoring","MORK3":"desert","MORK4":"traditional ecological knowledge","MORK5":"cultural burning","MORK6":" "}},
{"type":"Feature","geometry":{"type":"Point","coordinates":[16321950.077356985,-5168030.307357309]},"properties":{"PID":"P2","ID":"TSR_2_2_1","TITLE":"Saving the orange-bellied parrot","MORK1":"hollow nesting bird","MORK2":"nest box","MORK3":"predation","MORK4":"Tasmania","MORK5":"sugar glider","MORK6":" "}},
{"type":"Feature","geometry":{"type":"Point","coordinates":[16321950.077356985,-5168030.307357309]},"properties":{"PID":"P2","ID":"TSR_2_2_2","TITLE":"Saving the swift parrot","MORK1":"hollow nesting bird","MORK2":"nest box","MORK3":"predation","MORK4":"Tasmania","MORK5":"sugar glider","MORK6":"parasite"}},
{"type":"Feature","geometry":{"type":"Point","coordinates":[16321950.078262595,-5168030.305900902]},"properties":{"PID":"P2","ID":"TSR_2_2_3","TITLE":"Conservation and management of the endangered forty-spotted pardalote","MORK1":"hollow nesting bird","MORK2":"nest box","MORK3":"predation","MORK4":"Tasmania","MORK5":"disease","MORK6":"parasite"}},
{"type":"Feature","geometry":{"type":"Point","coordinates":[15000071.06942687,-2839834.1021526754]},"properties":{"PID":"P3","ID":"TSR_3_2_1","TITLE":"Improving threatened species monitoring","MORK1":"monitoring","MORK2":"adaptive management","MORK3":"ecological evidence","MORK4":"ecological recovery","MORK5":"adaptive monitoring","MORK6":"management"}},
{"type":"Feature","geometry":{"type":"Point","coordinates":[15000071.06942687,-2839834.1021526754]},"properties":{"PID":"P4","ID":"TSR_4_1_6_3","TITLE":"Practitioner’s guide for genetic management of translocated fauna","MORK1":"genetic management","MORK2":"reintroduction","MORK3":"translocation","MORK4":"genetic mixing","MORK5":"decision support tool","MORK6":"management plans"}},
{"type":"Feature","geometry":{"type":"Point","coordinates":[15000071.06942687,-2839834.1021526754]},"properties":{"PID":"P4","ID":"TSR_4_3","TITLE":"Threatened plant translocations","MORK1":"plants","MORK2":"restoration","MORK3":"recovery planning","MORK4":"synthesis","MORK5":"database","MORK6":"management plans"}},
{"type":"Feature","geometry":{"type":"Point","coordinates":[14778950.29390985,-2722110.150250158]},"properties":{"PID":"P4","ID":"TSR_4_4_1","TITLE":"Soil moisture for vulunerable threatened species","MORK1":"physiological tolerance","MORK2":"microhabitat","MORK3":"heat stress","MORK4":"refuge","MORK5":"feral cat","MORK6":"drought"}},
{"type":"Feature","geometry":{"type":"Point","coordinates":[14778950.29390985,-2722110.150250158]},"properties":{"PID":"P4","ID":"TSR_4_4_3","TITLE":"Using biophysical models to identify species refuges in responses to climate change","MORK1":"refuge","MORK2":"flying fox","MORK3":"amphibians","MORK4":"chytrid","MORK5":"heat-stress","MORK6":"environmental tolerance"}},
{"type":"Feature","geometry":{"type":"Point","coordinates":[15000071.06942687,-2839834.1021526754]},"properties":{"PID":"P6","ID":"TSR_6_3_6","TITLE":"Prioritising conservation efforts and communicating conservation opportunities in urban areas","MORK1":"urban ecology","MORK2":"community engagement","MORK3":"local government","MORK4":"recovery planning","MORK5":"public engagement","MORK6":" "}},
{"type":"Feature","geometry":{"type":"Point","coordinates":[15849066.543526022,-4536597.532815915]},"properties":{"PID":"P3","ID":"TSR_3_2_2_4","TITLE":"Bioacoustic monitoring of breeding in glossy and red-tailed black-cockatoos","MORK1":"monitoring","MORK2":"bioacoustics","MORK3":"woodland birds","MORK4":"conservation technology","MORK5":"species recovery","MORK6":"call recognition"}},
{"type":"Feature","geometry":{"type":"Point","coordinates":[15286399.805099977,-4271384.459124012]},"properties":{"PID":"P4","ID":"TSR_4_2_1","TITLE":"A national data base of threatened and invasive species on Australian Islands","MORK1":"island conservation","MORK2":"islands database","MORK3":"invasive species","MORK4":"species interactions","MORK5":"spatial mapping","MORK6":"prioritisation"}},
{"type":"Feature","geometry":{"type":"Point","coordinates":[16518546.3526963,-3291027.792052741]},"properties":{"PID":"P4","ID":"TSR_4_4_12","TITLE":"A national approach to the integration of koala spatial data to inform conservation planning","MORK1":"koala","MORK2":"distribution model","MORK3":"climate change","MORK4":"recovery plan","MORK5":"on-ground management","MORK6":"national recovery plan"}},
{"type":"Feature","geometry":{"type":"Point","coordinates":[17070479.928096607,-3322825.421628912]},"properties":{"PID":"P4","ID":"TSR_4_4_11","TITLE":"Using detection dog techniques to conserve Queensland's endangered montane species","MORK1":"black-tailed dusky antechinus","MORK2":"silver-headed antechinus","MORK3":"Bulburin macademia nut","MORK4":"detection dogs","MORK5":"Bulburin ringtailed gecko","MORK6":"montane rainforest"}},
{"type":"Feature","geometry":{"type":"Point","coordinates":[13869170.375692401,-2608189.883166891]},"properties":{"PID":"P3","ID":"TSR_3_2_2_2","TITLE":"Monitoring threatened species on Indigenous lands: Bilbies in the Martu Determination","MORK1":"monitoring","MORK2":"Indigenous knowledge","MORK3":"Indigenous rangers","MORK4":"greater bilby","MORK5":"fire management","MORK6":"distribution model"}},
{"type":"Feature","geometry":{"type":"Point","coordinates":[13037577.637796562,-3458307.070391707]},"properties":{"PID":"P3","ID":"TSR_4_1_6_2","TITLE":"Genetic management and population modelling of translocated fauna","MORK1":"mammals","MORK2":"genetics","MORK3":"population viability analysis","MORK4":"decision support tools","MORK5":"translocation","MORK6":"drought"}},
{"type":"Feature","geometry":{"type":"Point","coordinates":[13107034.39511596,-3939501.858445378]},"properties":{"PID":"P4","ID":"TSR_4_1_6_1","TITLE":"Can assisted gene flow increase the resilience of terrestrial-breeding frogs to a drying climate?","MORK1":"reproduction","MORK2":"frogs","MORK3":"climate change","MORK4":"assisted gene flow","MORK5":"drought","MORK6":"local adaptation"}},
{"type":"Feature","geometry":{"type":"Point","coordinates":[18695933.325935014,-3380035.670919267]},"properties":{"PID":"P4","ID":"TSR_4_1_9","TITLE":"Genetic analysis of the Norfolk Island morepork and green parrot","MORK1":" ","MORK2":"morepork","MORK3":"green parrot","MORK4":"genetics","MORK5":"species recovery","MORK6":"island conservation"}}
]}